py_quic/__init__.py
py_quic/core.py
py_quic-0.1.5.dist-info/licenses/LICENSE
py_quic-0.1.5.dist-info/METADATA
py_quic-0.1.5.dist-info/WHEEL
py_quic-0.1.5.dist-info/top_level.txt
py_quic-0.1.5.dist-info/RECORD
