Metadata-Version: 2.4
Name: py-quic
Version: 0.1.5
Summary: Quic client/server protocol wrapper for Python.
Author: Pablo Picouto Garcia
License: Copyright (c) 2025 Pablo
Project-URL: Homepage, https://github.com/politrons/Dive-into-Python
Project-URL: Issues, https://github.com/politrons/Dive-into-Python
Keywords: quic,http3,udp,asyncio,networking
Classifier: Programming Language :: Python :: 3
Classifier: License :: OSI Approved :: MIT License
Classifier: Typing :: Typed
Requires-Python: >=3.10
License-File: LICENSE
Requires-Dist: aioquic
Dynamic: license-file
